markovmusic/__init__.py
markovmusic/composer.py
markovmusic/utils.py
markovmusic-0.1.0.dist-info/licenses/LICENSE.txt
markovmusic-0.1.0.dist-info/METADATA
markovmusic-0.1.0.dist-info/WHEEL
markovmusic-0.1.0.dist-info/top_level.txt
markovmusic-0.1.0.dist-info/RECORD
