Metadata-Version: 2.4
Name: markovmusic
Version: 0.1.0
Summary: Generate music by training a Markov chain on your own MIDI files!
Author-email: Ronit Kunkolienker <ronitkunk@gmail.com>
License: MIT License
Requires-Python: >=3.8
License-File: LICENSE.txt
Requires-Dist: numpy
Requires-Dist: sounddevice
Requires-Dist: scipy
Requires-Dist: mido
Dynamic: license-file
